beanahead/__init__.py
beanahead/_version.py
beanahead/config.py
beanahead/errors.py
beanahead/expired.py
beanahead/reconcile.py
beanahead/rx_txns.py
beanahead/utils.py
beanahead/plugins/__init__.py
beanahead/plugins/rx_txn_plugin.py
beanahead/scripts/__init__.py
beanahead/scripts/cli.py
beanahead-0.5.1.dist-info/licenses/LICENSE.txt
beanahead-0.5.1.dist-info/METADATA
beanahead-0.5.1.dist-info/WHEEL
beanahead-0.5.1.dist-info/entry_points.txt
beanahead-0.5.1.dist-info/top_level.txt
beanahead-0.5.1.dist-info/RECORD
