Metadata-Version: 2.4
Name: beanahead
Version: 0.5.1
Summary: Beancount extension for future transactions
Author: Marcus Read
Author-email: marcusaread.prog@proton.me
License-Expression: MIT
Project-URL: homepage, https://github.com/maread99/beanahead
Project-URL: documentation, https://github.com/maread99/beanahead
Project-URL: Issue Tracker, https://github.com/maread99/beanahead/issues
Project-URL: Source Code, https://github.com/maread99/beanahead
Keywords: accounting,beancount,ledger,finance
Classifier: Development Status :: 4 - Beta
Classifier: Intended Audience :: Developers
Classifier: Intended Audience :: End Users/Desktop
Classifier: Intended Audience :: Financial and Insurance Industry
Classifier: Natural Language :: English
Classifier: Operating System :: OS Independent
Classifier: Programming Language :: Python
Classifier: Programming Language :: Python :: 3
Classifier: Programming Language :: Python :: 3 :: Only
Classifier: Programming Language :: Python :: 3.10
Classifier: Programming Language :: Python :: 3.11
Classifier: Programming Language :: Python :: 3.12
Classifier: Programming Language :: Python :: 3.13
Classifier: Programming Language :: Python :: Implementation :: CPython
Classifier: Topic :: Office/Business :: Financial :: Accounting
Requires-Python: <4,>=3.10
License-File: LICENSE.txt
Requires-Dist: beancount>=2.3.6
Requires-Dist: beangulp>=0.1
Requires-Dist: pandas>=2.2
Dynamic: license-file
